[
  {
    "section": "here-now",
    "links": [
      {
        "author": "The Irish Times",
        "date": "24 Mar 2025",
        "title": "US magazine editor says he was added to Trump advisers' text group on bombing Houthis",
        "url": "https://www.irishtimes.com/world/us/2025/03/24/atlantic-magazine-editor-says-he-was-added-to-trump-advisers-text-group-on-bombing-houthis/",
        "tags": ""
      },
      {
        "author": "Andrew Solender, Hans Nichols, Stephen Neukam, Axios",
        "date": "24 Mar 2025",
        "title": "'Heads should roll': Congress erupts over stunning Trump admin leak",
        "url": "https://www.axios.com/2025/03/24/atlantic-yemen-signal-hegseth-jeffrey-goldberg",
        "tags": ""
      },
      {
        "author": "Sasha Abramsky, Truthout",
        "date": "24 Mar 2025",
        "title": "Trump Ramps Up Effort to Intimidate Judges Amid Their Growing Pushback",
        "url": "https://truthout.org/articles/trump-ramps-up-effort-to-intimidate-judges-amid-their-growing-pushback/",
        "tags": ""
      },
      {
        "author": "Sam Baker, Axios",
        "date": "23 Mar 2025",
        "title": "Trump moves closer to court crisis",
        "url": "https://www.axios.com/2025/03/23/trump-boasberg-courts-constitutional-crisis",
        "tags": ""
      },
      {
        "author": "Mike Scarcella, Andrew Goudsward, and Sara Merken, Reuters",
        "date": "22 Mar 2025",
        "title": "Trump targets lawyers in immigration cases, lawsuits against administration",
        "url": "https://www.reuters.com/legal/trump-signs-memo-aimed-preventing-abuse-legal-system-federal-courts-2025-03-22/",
        "tags": ""
      },
      {
        "author": "Chris Walker, Truthout",
        "date": "21 Mar 2025",
        "title": "Elon Musk Donates to GOP Lawmakers After They Back His Calls to Impeach Judges",
        "url": "https://truthout.org/articles/elon-musk-donates-to-gop-lawmakers-after-they-back-his-calls-to-impeach-judges/",
        "tags": ""
      },
      {
        "author": "Andrea Hsu, NPR",
        "date": "21 Mar 2025",
        "title": "How Trump's firings could upend a 90-year-old Supreme Court ruling limiting his power",
        "url": "https://www.npr.org/2025/03/21/nx-s1-5333325/ftc-trump-firings-supreme-court",
        "tags": ""
      },
      {
        "author": "Sasha Abramsky, Truthout",
        "date": "20 Mar 2025",
        "title": "Trump and DOGE's Attacks on CFPB Will Help Financial Industry Prey on Consumers",
        "url": "https://truthout.org/articles/trump-and-doges-attacks-on-cfpb-will-help-financial-industry-prey-on-consumers/",
        "tags": ""
      },
      {
        "author": "Zane McNeill, Truthout",
        "date": "20 Mar 2025",
        "title": "Columbia University Historians Warn of Trump's Threat to Academic Freedom",
        "url": "https://truthout.org/articles/columbia-university-historians-warn-of-trumps-threat-to-academic-freedom/",
        "tags": ""
      },
      {
        "author": "Democracy Now!",
        "date": "20 Mar 2025",
        "title": "'Murder the Truth': David Enrich on Right-Wing Campaign to Silence Journalists & Protect the Powerful",
        "url": "https://www.democracynow.org/2025/3/20/nyt_v_sullivan_press_freedom",
        "tags": ""
      },
      {
        "author": "Stephen Engelberg, ProPublica",
        "date": "20 Mar 2025",
        "title": "The October Story That Outlined Exactly What the Trump Administration Would Do to the Federal Bureaucracy",
        "url": "https://www.propublica.org/article/propublica-russell-vought-prophetic-trump-second-term",
        "tags": ""
      },
      {
        "author": "Collin Binkley and Chris Megerian, Associated Press",
        "date": "20 Mar 2025",
        "title": "Trump will order a plan to shut down the US Education Department",
        "url": "https://apnews.com/article/trump-education-department-shutdown-b1d25a2e1bdcd24cfde8ad8b655b9843",
        "tags": ""
      },
      {
        "author": "Kenny Stancil, Revolving Door Project",
        "date": "19 Mar 2025",
        "title": "DOGE Is Going to Kill a Lot of Americans",
        "url": "https://therevolvingdoorproject.org/doge-is-going-to-kill-a-lot-of-americans/",
        "tags": ""
      },
      {
        "author": "David Corn, Mother Jones",
        "date": "19 Mar 2025",
        "title": "Trump and Musk Are Running a Disinformation Campaign on Social Security",
        "url": "https://www.motherjones.com/politics/2025/03/trump-musk-doge-disinformation-campaign-social-security/",
        "tags": ""
      },
      {
        "author": "Hannah Story Brown, Revolving Door Project",
        "date": "19 Mar 2025",
        "title": "Trump Officials Are Openly Defying Judges' Orders",
        "url": "https://therevolvingdoorproject.org/trump-officials-are-openly-defying-judges-orders/",
        "tags": ""
      },
      {
        "author": "Andy Kroll, ProPublica",
        "date": "19 Mar 2025",
        "title": "Emails Reveal Top IRS Lawyer Warned Trump Firings Were a 'Fraud' on the Courts",
        "url": "https://www.propublica.org/article/trump-irs-firings-doge-fraud-law-job-performance",
        "tags": ""
      },
      {
        "author": "Erin Banco and Mari Saito, Reuters",
        "date": "19 Mar 2025",
        "title": "US suspends some efforts to counter Russian sabotage as Trump moves closer to Putin",
        "url": "https://www.reuters.com/world/us-suspends-some-efforts-counter-russian-sabotage-trump-moves-closer-putin-2025-03-19/",
        "tags": ""
      },
      {
        "author": "Brandon Novick, Center for Economic and Policy Research",
        "date": "18 Mar 2025",
        "title": "Blame the Supreme Court for Elon Musk's Corrupt Control of the Trump Administration",
        "url": "https://cepr.net/publications/corrupt-control-of-the-trump-administration/",
        "tags": ""
      },
      {
        "author": "Vittoria Elliott, WIRED",
        "date": "18 Mar 2025",
        "title": "'It's a Heist': Real Federal Auditors Are Horrified by DOGE",
        "url": "https://www.wired.com/story/federal-auditors-doge-elon-musk/",
        "tags": ""
      },
      {
        "author": "Chris Walker, Truthout",
        "date": "18 Mar 2025",
        "title": "Trump Demands Impeachment of Judge Who Ruled to Block His Deportation Orders",
        "url": "https://truthout.org/articles/trump-demands-impeachment-of-judge-who-ruled-to-block-his-deportation-orders/",
        "tags": ""
      },
      {
        "author": "Erin Alberty, Axios",
        "date": "17 Mar 2025",
        "title": "Navajo Code Talkers disappear from military websites after Trump DEI order",
        "url": "https://www.axios.com/local/salt-lake-city/2025/03/17/navajo-code-talkers-trump-dei-military-websites-wwii",
        "tags": ""
      },
      {
        "author": "Zane McNeill, Truthout",
        "date": "17 Mar 2025",
        "title": "Trump Threatens Media, Opponents With Legal Action in DOJ Speech",
        "url": "https://truthout.org/articles/trump-threatens-media-opponents-with-legal-action-in-doj-speech/",
        "tags": ""
      },
      {
        "author": "Emily Peck, Axios",
        "date": "17 Mar 2025",
        "title": "Leaked memo: DOGE plots to cut Social Security phone support",
        "url": "https://www.axios.com/2025/03/17/social-security-trump-doge",
        "tags": ""
      },
      {
        "author": "Democracy Now!",
        "date": "17 Mar 2025",
        "title": "Rep. Jamie Raskin: Trump’s Attacks on Critics & Press Are Part of the 'Authoritarian Playbook'",
        "url": "https://www.democracynow.org/2025/3/17/jamie_raskin_trump_constitutional_crisis",
        "tags": ""
      },
      {
        "author": "Kate Yoder, Mother Jones",
        "date": "17 Mar 2025",
        "title": "The Tragedy—and Tyranny—of Donald Trump's War on 'Woke'",
        "url": "https://www.motherjones.com/politics/2025/03/trump-doge-attack-woke-dei-keywords-ai-search/",
        "tags": ""
      },
      {
        "author": "Marc Caputo, Axios",
        "date": "16 Mar 2025",
        "title": "How the White House ignored a judge's order to turn back deportation flights",
        "url": "https://www.axios.com/2025/03/16/trump-white-house-defy-judge-deport-venezuelans",
        "tags": ""
      },
      {
        "author": "Rebecca Kheel, Military.com",
        "date": "14 Mar 2025",
        "title": "National Mall Protest Against Trump Administration Includes Veterans Hurt by Cuts",
        "url": "https://www.military.com/daily-news/2025/03/14/veterans-protest-trump-administrations-slashing-of-federal-government.html",
        "tags": ""
      },
      {
        "author": "Democracy Now!",
        "date": "14 Mar 2025",
        "title": "'Imperialism and Totalitarianism Go Hand in Hand': M. Gessen on Trump’s Policies at Home & Abroad",
        "url": "https://www.democracynow.org/2025/3/14/m_gessen",
        "tags": ""
      },
      {
        "author": "Nina Totenberg, NPR",
        "date": "14 Mar 2025",
        "title": "Trump takes birthright citizenship to the Supreme Court",
        "url": "https://www.npr.org/2025/03/14/nx-s1-5327552/trump-takes-birthright-citizenship-to-the-supreme-court",
        "tags": ""
      },
      {
        "author": "Brian Barrett, WIRED",
        "date": "13 Mar 2025",
        "title": "The United States of Elon Musk Inc.",
        "url": "https://www.wired.com/story/elon-musk-donald-trump-doge-congress-takeover/",
        "tags": ""
      },
      {
        "author": "Zolan Kanno-Youngs, Hamed Aleaziz, The Irish Times",
        "date": "13 Mar 2025",
        "title": "How Donald Trump is using fear, obscure laws and immigration agents to crack down on dissent",
        "url": "https://www.irishtimes.com/world/us/2025/03/13/how-donald-trump-is-using-fear-obscure-laws-and-immigration-agents-to-crack-down-on-dissent/",
        "tags": ""
      },
      {
        "author": "Isabela Dias, Mother Jones",
        "date": "13 Mar 2025",
        "title": "Trump’s American Caste System",
        "url": "https://www.motherjones.com/politics/2025/03/trump-caste-america-birthright-citizenship/",
        "tags": ""
      },
      {
        "author": "Joseph Cox, 404 Media",
        "date": "12 Mar 2025",
        "title": "The 200+ Sites an ICE Surveillance Contractor is Monitoring",
        "url": "https://www.404media.co/the-200-sites-an-ice-surveillance-contractor-is-monitoring/?ref=daily-stories-newsletter",
        "tags": ""
      },
      {
        "author": "Russell Contreras, Brittany Gibson, Avery Lotz, Axios",
        "date": "11 Mar 2025",
        "title": "Columbia protest leader's arrest tests immigrants' free-speech rights",
        "url": "https://www.axios.com/2025/03/11/columbia-protest-activist-arrest-free-speech",
        "tags": ""
      },
      {
        "author": "Christina A. Cassidy, Associated Press",
        "date": "10 Mar 2025",
        "title": "Trump administration halts funding for two cybersecurity efforts, including one for elections",
        "url": "https://apnews.com/article/election-security-cisa-trump-kristi-noem-6c437543f5d26d890704e5f2a8400502",
        "tags": ""
      },
      {
        "author": "Alexa St. John, Associated Press",
        "date": "10 Mar 2025",
        "title": "Trump DOT chief rejects inclusion of environmental justice factors in infrastructure decisions",
        "url": "https://apnews.com/article/trump-sean-duffy-environmental-justice-infrastructure-850bc20146a50aacaa9dbe6bdcf73883",
        "tags": ""
      },
      {
        "author": "Jeff Nesbit, The Contrarian",
        "date": "10 Mar 2025",
        "title": "Destroying Social Security from within",
        "url": "https://contrarian.substack.com/p/destroying-social-security-from-within",
        "tags": ""
      },
      {
        "author": "Annie Waldman and Lisa Song, ProPublica",
        "date": "10 Mar 2025",
        "title": "National Cancer Institute Employees Can’t Publish Information on These Topics Without Special Approval",
        "url": "https://www.propublica.org/article/national-cancer-institute-flagged-topics-vaccines-autism-rfk-jr",
        "tags": ""
      },
      {
        "author": "Mike Ludwig, Truthout",
        "date": "09 Mar 2025",
        "title": "As Mass Incarceration of Immigrants Rises, Detention Centers Eye New Contracts",
        "url": "https://truthout.org/articles/as-mass-incarceration-of-immigrants-rises-detention-centers-eye-new-contracts/",
        "tags": ""
      },
      {
        "author": "Andrea Hsu, NPR",
        "date": "08 Mar 2025",
        "title": "States sue Trump administration over mass firings of federal employees",
        "url": "https://www.npr.org/2025/03/08/nx-s1-5321864/trump-federal-employees-lawsuit-states",
        "tags": ""
      },
      {
        "author": "Jonaki Mehta, NPR",
        "date": "07 Mar 2025",
        "title": "Trump signs executive action targeting public service loan program",
        "url": "https://www.npr.org/2025/03/07/nx-s1-5321313/trump-executive-action-public-service-loan-program",
        "tags": ""
      },
      {
        "author": "Karen Yourish, Annie Daniel, Saurabh Datar, Isaac White, and Lazaro Gamio, New York Times",
        "date": "07 Mar 2025",
        "title": "These Words Are Disappearing in the New Trump Administration",
        "url": "https://www.nytimes.com/interactive/2025/03/07/us/trump-federal-agencies-websites-words-dei.html",
        "tags": ""
      },
      {
        "author": "Schuyler Mitchell, Truthout",
        "date": "07 Mar 2025",
        "title": "After Failures in the Courts, the GOP Is Threatening Sanctuary City Mayors",
        "url": "https://truthout.org/articles/after-failures-in-the-courts-the-gop-is-threatening-sanctuary-city-mayors/",
        "tags": ""
      },
      {
        "author": "Justin Elliott, Joshua Kaplan, and Alex Mierjeski, ProPublica",
        "date": "06 Mar 2025",
        "title": "Secretive D.C. Influence Project Appears to Be Running a Group House for Right-Wing Lawmakers",
        "url": "https://www.propublica.org/article/roommates-steve-berger-mike-johnson-andy-ogles-right-wing-influence-townhouse",
        "tags": ""
      },
      {
        "author": "Tara Copp, Lolita C. Baldor, and Kevin Vineys, Associated Press",
        "date": "06 Mar 2025",
        "title": "War heroes and military firsts are among 26,000 images flagged for removal in Pentagon's DEI purge",
        "url": "https://apnews.com/article/dei-purge-images-pentagon-diversity-women-black-8efcfaec909954f4a24bad0d49c78074",
        "tags": ""
      },
      {
        "author": "Lisa Friedman, New York Times",
        "date": "06 Mar 2025",
        "title": "National Parks Had a Record Year. Trump Officials Appear to Want It Kept Quiet",
        "url": "https://www.nytimes.com/2025/03/06/climate/national-parks-record-visitors-trump.html",
        "tags": ""
      },
      {
        "author": "David Gilbert, WIRED",
        "date": "06 Mar 2025",
        "title": "Social Security Workers Aren’t Allowed to Read This Story",
        "url": "https://www.wired.com/story/social-security-workers-arent-allowed-to-read-this-story/",
        "tags": ""
      },
      {
        "author": "Sharon Lerner, ProPublica",
        "date": "06 Mar 2025",
        "title": "Industry-Backed Legislation Would Bar the Use of Science Behind Hundreds of Environmental Protections",
        "url": "https://www.propublica.org/article/legislation-targets-epa-science-toxic-chemicals",
        "tags": ""
      },
      {
        "author": "Pema Levy, Mother Jones",
        "date": "05 Mar 2025",
        "title": "The Supreme Court Is Just One Vote Shy of Making Trump and Musk Kings",
        "url": "https://www.motherjones.com/politics/2025/03/usaid-supreme-court-doge/",
        "tags": ""
      },
      {
        "author": "Dave Lawler, Axios",
        "date": "04 Mar 2025",
        "title": "Trump's stunning string of Putin-friendly moves",
        "url": "https://www.axios.com/2025/03/04/trump-russia-ukraine-policy-pro-putin",
        "tags": ""
      },
      {
        "author": "Chris Walker, Truthout",
        "date": "03 Mar 2025",
        "title": "Elon Musk Spreads Falsehoods About Social Security, Calling It a 'Ponzi Scheme'",
        "url": "https://truthout.org/articles/elon-musk-spreads-falsehoods-about-social-security-calling-it-a-ponzi-scheme/",
        "tags": ""
      },
      {
        "author": "Democracy Now!",
        "date": "03 Mar 2025",
        "title": "U.S.-Europe Rift Widens as Russia Welcomes Trump's Shifting Ukraine Stance Following Zelensky Clash",
        "url": "https://www.democracynow.org/2025/3/3/ukraine_russia_trump_vance_putin",
        "tags": ""
      },
      {
        "author": "David Folkenflik, NPR",
        "date": "01 Mar 2025",
        "title": "Voice of America bias inquiry sparks concerns of political meddling",
        "url": "https://www.npr.org/2025/03/01/g-s1-51489/voice-of-america-bias-inquiry",
        "tags": ""
      },
      {
        "author": "Radio France Internationale",
        "date": "01 Mar 2025",
        "title": "European allies rally behind Ukraine after White House clash",
        "url": "https://www.rfi.fr/en/international/20250301-european-allies-rally-behind-ukraine-after-white-house",
        "tags": ""
      },
      {
        "author": "Stephanie Kirchgaessner, The Guardian",
        "date": "01 Mar 2025",
        "title": "Trump administration retreats in fight against Russian cyber threats",
        "url": "https://www.theguardian.com/us-news/2025/feb/28/trump-russia-hacking-cyber-security",
        "tags": ""
      },
      {
        "author": "Brian Barrett, WIRED",
        "date": "27 Feb 2025",
        "title": "The DOGE Takeover Is Worse Than You Think",
        "url": "https://www.wired.com/story/doge-worse-than-you-think/",
        "tags": ""
      },
      {
        "author": "Corey G. Johnson, Anna Donlan, ProPublica",
        "date": "27 Feb 2025",
        "title": "Targeted: How Cambridge Analytica Used Intimate Data to Exploit Gun Owners' Private Lives",
        "url": "https://projects.propublica.org/gun-owners-cambridge-analytica-data-psychological-profiles-privacy/",
        "tags": ""
      },
      {
        "author": "Sasha Abramsky, Truthout",
        "date": "26 Feb 2025",
        "title": "Trump Team’s Plan to “Make America Great Again” Is to Eviscerate Public Safety",
        "url": "https://truthout.org/articles/trump-teams-plan-to-make-america-great-again-is-to-eviscerate-public-safety/",
        "tags": ""
      },
      {
        "author": "Zane McNeill, Truthout",
        "date": "25 Feb 2025",
        "title": "Elon Musk Calls for Impeachment of Judges Who Oppose Trump Policies",
        "url": "https://truthout.org/articles/elon-musk-calls-for-impeachment-of-judges-who-oppose-trump-policies/",
        "tags": ""
      },
      {
        "author": "Mike Ludwig, Truthout",
        "date": "25 Feb 2025",
        "title": "Trump Demonstrates Profound Ignorance With Remarks on Ukraine War Anniversary",
        "url": "https://truthout.org/articles/trump-demonstrates-profound-ignorance-with-remarks-on-ukraine-war-anniversary/",
        "tags": ""
      },
      {
        "author": "Anna Merlan, Mother Jones",
        "date": "25 Feb 2025",
        "title": "Meet the New State Media",
        "url": "https://www.motherjones.com/politics/2025/02/donald-trump-press-room-conservative-media/",
        "tags": ""
      },
      {
        "author": "Nicole A. Ozer, The Contrarian",
        "date": "25 Feb 2025",
        "title": "Will We Let a Digital Coup Against Democracy Prevail?",
        "url": "https://contrarian.substack.com/p/will-we-let-a-digital-coup-against",
        "tags": ""
      },
      {
        "author": "Stephen Engelberg, ProPublica",
        "date": "24 Feb 2025",
        "title": "The Trump Administration Keeps Citing an Untrue Stat as It Targets Federal Workers",
        "url": "https://www.propublica.org/article/federal-employees-work-from-home-trump-myth",
        "tags": ""
      },
      {
        "author": "Jonathan Alter, OLD GOATS with Jonathan Alter",
        "date": "24 Feb 2025",
        "title": "Tsar Trump Thinks He’s the State",
        "url": "https://oldgoats.substack.com/cp/157920330",
        "tags": ""
      },
      {
        "author": "David Corn, Democracy Now!",
        "date": "24 Feb 2025",
        "title": "Democrats Are MIA—Just When the Country Needs Them to Counter the Trump-Musk Blitzkrieg",
        "url": "https://www.motherjones.com/politics/2025/02/democrats-missing-in-action-schumer-jeffries-trump-musk-doge/",
        "tags": ""
      },
      {
        "author": "Christine Fernando, Associated Press",
        "date": "24 Feb 2025",
        "title": "The young techies behind DOGE are a lightning rod for criticism but also a youth magnet for the GOP",
        "url": "https://apnews.com/article/doge-young-voters-trump-musk-republicans-democrats-6a741bd4df1ef0a80c76239cb019e60f",
        "tags": ""
      },
      {
        "author": "Madison Pauly, Mother Jones",
        "date": "24 Feb 2025",
        "title": "LGBTQ Federal Workers Brace for a McCarthyist Purge",
        "url": "https://www.motherjones.com/politics/2025/02/queer-trans-federal-workers-fear-lgbtq-purge-lavender-scare/A",
        "tags": ""
      },
      {
        "author": "Avery Lotz, Axios",
        "date": "24 Feb 2025",
        "title": "NATO prepares for a post-America alliance",
        "url": "https://www.axios.com/2025/02/24/nato-trump-new-american-alliance",
        "tags": ""
      },
      {
        "author": "Democracy Now!",
        "date": "24 Feb 2025",
        "title": "Trump Team Purges Military Leadership, Lawyers",
        "url": "https://www.democracynow.org/2025/2/24/headlines/trump_team_purges_military_leadership_lawyersA",
        "tags": ""
      },
      {
        "author": "Julianne McShane, Mother Jones",
        "date": "23 Feb 2025",
        "title": "Trump Officials Remind Federal Employees That Elon Musk Is Not Their Boss",
        "url": "https://www.motherjones.com/politics/2025/02/doge-email-last-week-elon-musk/",
        "tags": ""
      },
      {
        "author": "Emanuel Maiberg, 404 Media",
        "date": "21 Feb 2025",
        "title": "'The Bigotry Is Astounding:' Engineers Waste Time and Money Scanning .Gov Sites for 'Transgender' and Other Terms",
        "url": "https://www.404media.co/the-bigotry-is-astounding-engineers-waste-time-and-money-scanning-gov-sites-for-transgender-and-other-terms/",
        "tags": "bigotry, memory hole"
      },
      {
        "author": "Jonathan Pie",
        "date": "21 Feb 2025",
        "title": "The Art of the Deal",
        "url": "https://www.youtube.com/watch?v=Jk0nUUqG_Ag",
        "tags": ""
      },
      {
        "author": "Amy Goodman & Denis Moynihan, Democracy Now!",
        "date": "20 Feb 2025",
        "title": "Dark Shadows of Fascism Over Germany and the U.S.",
        "url": "https://www.democracynow.org/2025/2/20/dark_shadows_of_fascism_over_germany",
        "tags": ""
      },
      {
        "author": "Robert Reich, The Guardian",
        "date": "20 Feb 2025",
        "title": "In the global clash between democracy and oligarchy, the US is switching sides",
        "url": "https://www.theguardian.com/commentisfree/2025/feb/20/trump-musk-oligarchy-russia-far-right",
        "tags": "sometimes the rich eat you"
      },
      {
        "author": "Maya Goldman, Axios",
        "date": "20 Feb 2025",
        "title": "HHS redefines sex as 'immutable' in new guidance",
        "url": "https://www.axios.com/2025/02/20/hhs-redefines-sex-as-immutable",
        "tags": "doublespeak"
      },
      {
        "author": "Kim Zetter, WIRED",
        "date": "19 Feb 2025",
        "title": "DOGE Now Has Access to the Top US Cybersecurity Agency",
        "url": "https://www.wired.com/story/doge-cisa-coristine-cybersecurity/",
        "tags": ""
      },
      {
        "author": "David Smith, The Guardian",
        "date": "19 Feb 2025",
        "title": "'The deification of Trump will be complete' at CPAC 20",
        "url": "https://www.theguardian.com/us-news/2025/feb/19/trump-cpac-conference",
        "tags": ""
      },
      {
        "author": "Benjamin Oreskes, New York Times",
        "date": "19 Feb 2025",
        "title": "'Long Live the King': Trump Likens Himself to Royalty on Truth Social",
        "url": "https://www.nytimes.com/2025/02/19/us/politics/trump-king-image.html",
        "tags": ""
      },
      {
        "author": "Zach Montague, New York Times",
        "date": "18 Feb 2025",
        "title": "Education Dept. Gives Schools Two Weeks to Eliminate Race-Based Programs",
        "url": "https://www.nytimes.com/2025/02/17/us/politics/education-dept-race-based-programs.html",
        "tags": ""
      },
      {
        "author": "Doina Chiacu, Reuters",
        "date": "16 Feb 2025",
        "title": "Trump: If it saves the country, it's not illegal",
        "url": "https://www.reuters.com/world/us/trump-if-it-saves-country-its-not-illegal-2025-02-16/",
        "tags": ""
      },
      {
        "author": "Mark Sherman and Lindsay Whitehurst, Associated Press",
        "date": "16 Feb 2025",
        "title": "Trump administration wants the Supreme Court to let the firing of whistleblower agency head proceed",
        "url": "https://apnews.com/article/supreme-court-trump-administration-f2455731efaf92678940bf11c63f7fe8",
        "tags": ""
      },
      {
        "author": "Will Weissert, Josh Boak and Lindsay Whitehurst, Associated Press",
        "date": "15 Feb 2025",
        "title": "Trump moves with dizzying speed on his to-do list. But there are warning signs in his first month",
        "url": "https://apnews.com/article/trump-firings-tariffs-lawsuits-economy-ukraine-putin-19b79f62ad7c9d51cfb1f0551953051e",
        "tags": ""
      },
      {
        "author": "Emanuel Maiberg, Jason Koebler, 404 Media",
        "date": "14 Feb 2025",
        "title": "Trump Admin Adds Note Rejecting 'Gender Ideology' on Sites Court Ordered Them to Restore",
        "url": "https://www.404media.co/trump-admin-adds-note-rejecting-gender-ideology-on-sites-court-ordered-them-to-restore",
        "tags": ""
      },
      {
        "author": "Samantha Cole, 404 Media",
        "date": "14 Feb 2025",
        "title": "Researcher Captures Contents of 'DEI.gov' Before It Was Hidden Behind a Password",
        "url": "https://www.404media.co/dei-waste-gov-doge-list-behind-password/",
        "tags": ""
      },
      {
        "author": "David Bauder, Associated Press",
        "date": "12 Feb 2025",
        "title": "White House bars AP reporter from Oval Office because of AP style policy on 'Gulf of America'",
        "url": "https://apnews.com/article/trump-ap-journalism-first-amendment-8a83d8b506053249598e807f8e91e1ae",
        "tags": ""
      },
      {
        "author": "Anthony Zurcher &amp; Kayla Epstein, BBC News",
        "date": "12 Feb 2025",
        "title": "Legal showdown looms as Trump tests limits of presidential power",
        "url": "https://www.bbc.com/news/articles/c70kd686k2do",
        "tags": ""
      },
      {
        "author": "Jason Koebler, 404 Media",
        "date": "11 Feb 2025",
        "title": "Wikipedia Prepares for 'Increase in Threats' to US Editors From Musk and His Allies",
        "url": "https://www.404media.co/wikipedia-prepares-for-increase-in-threats-to-us-editors-from-musk-and-his-allies/",
        "tags": ""
      },
      {
        "author": "Makena Kelly and Dhruv Mehrotra, WIRED",
        "date": "11 Feb 2025",
        "title": "Dozens of CFPB Workers Fired in After-Hours Blitz",
        "url": "https://www.wired.com/story/dozens-of-cfpb-workers-terminated-in-after-hours-firing-blitz",
        "tags": ""
      },
      {
        "author": "Elena Moore, NPR",
        "date": "11 Feb 2025",
        "title": "Trump and Musk appear together in the Oval Office to defend the work of DOGE",
        "url": "https://www.npr.org/2025/02/11/nx-s1-5293504/trump-musk-doge-oval-office",
        "tags": ""
      },
      {
        "author": "Adam Liptak, New York Times",
        "date": "10 Feb 2025",
        "title": "Trump’s Actions Have Created a Constitutional Crisis, Scholars Say",
        "url": "https://www.nytimes.com/2025/02/10/us/politics/trump-constitutional-crisis.html",
        "tags": ""
      },
      {
        "author": "Josh Marcus, Independent",
        "date": "10 Feb 2025",
        "title": "Civil rights attorney sounds alarm after video shows ICE agents covering cameras during immigration raids",
        "url": "https://www.independent.co.uk/news/world/americas/us-politics/ice-raid-migrants-civil-rights-video-b2694712.html",
        "tags": ""
      },
      {
        "author": "Robert E. RubinLawrence H. SummersTimothy F. GeithnerJacob J. Lew and Janet L. Yellen - NYT Guest Post",
        "date": "10 Feb 2025",
        "title": "Five Former Treasury Secretaries: Our Democracy Is Under Siege",
        "url": "https://www.nytimes.com/2025/02/10/opinion/treasure-secretaries-doge-musk.html",
        "tags": ""
      },
      {
        "author": "Jason Koebler, 404 Media",
        "date": "07 Feb 2025",
        "title": "Trump Fires National Archives Director Colleen Shogan",
        "url": "https://www.404media.co/trump-fires-national-archives-director-colleen-shogan/",
        "tags": ""
      },
      {
        "author": "David Smith, The Guardian",
        "date": "07 Feb 2025",
        "title": "Trump hints Musk 'Doge' team has free rein with Pentagon next in line for cuts",
        "url": "https://www.theguardian.com/us-news/2025/feb/07/trump-elon-musk-doge-agency",
        "tags": ""
      },
      {
        "author": "The Big Picture",
        "date": "06 Feb 2025",
        "title": "Leaning Into Lawlessness: Donald Trump is refusing to follow laws he doesn't like. The courts and Congress are pushing back",
        "url": "https://thinkbigpicture.substack.com/p/trump-musk-lawless-orders",
        "tags": ""
      },
      {
        "author": "Eloise Goldsmith, Common Dreams",
        "date": "05 Feb 2025",
        "title": "'Be Loud. Stay Peaceful': Anti-Trump 'Movement 50501' Protests Take Place Nationwide",
        "url": "https://www.commondreams.org/news/movement-50501-protests",
        "tags": ""
      },
      {
        "author": "Tom Gerken, BBC News",
        "date": "05 Feb 2025",
        "title": "Reddit community banned as user spat with Musk intensifies",
        "url": "https://www.bbc.com/news/articles/czrlep5xpmzo",
        "tags": ""
      },
      {
        "author": "Tyler McBrien, NYT Opinion",
        "date": "05 Feb 2025",
        "title": "What Is 'State Capture'? A Warning for Americans.",
        "url": "https://www.nytimes.com/2025/02/05/opinion/elon-musk-donald-trump-government.html",
        "tags": ""
      },
      {
        "author": "Michel Martin, Ally Schweitzer, NPR",
        "date": "04 Feb 2025",
        "title": "Public needs to rise up to fight 'constitutional crisis,' says Democratic senator",
        "url": "https://www.npr.org/2025/02/04/nx-s1-5285491/sen-chris-murphy-discusses-the-power-of-congress-as-a-check-on-the-president",
        "tags": ""
      },
      {
        "author": "Chris Megerian, Associated Press",
        "date": "04 Feb 2025",
        "title": "Elon Musk tightens grip on federal government as Democrats raise alarms",
        "url": "https://apnews.com/article/elon-musk-donald-trump-doge-21153a742fbad86284369bb173ec343c",
        "tags": ""
      },
      {
        "author": "The God Podcast",
        "date": "03 Feb 2025",
        "title": "People Rally Outside USAID Building to Confront Elon Musk",
        "url": "https://www.thegodpodcast.com/p/people-rally-outside-usaid-building",
        "tags": ""
      },
      {
        "author": "Democracy Now!",
        "date": "03 Feb 2025",
        "title": "Is Elon Musk Staging a Coup? Unelected Billionaire Seizes Control at Treasury Dept. & Other Agencies",
        "url": "https://www.democracynow.org/2025/2/3/elon_musk_gov",
        "tags": ""
      },
      {
        "author": "Lee Moran, Huffpost",
        "date": "03 Feb 2025",
        "title": "Alexandria Ocasio-Cortez Sounds 'Five Alarm Fire' Over Latest Elon Musk News",
        "url": "https://www.huffpost.com/entry/alexandria-ocasio-cortez-five-alarm-fire_n_67a09574e4b0bef3e6d5754d",
        "tags": ""
      },
      {
        "author": "Jason Koebler, 404 Media",
        "date": "23 Jan 2025",
        "title": "GitHub Is Showing the Trump Administration Scrubbing Government Web Pages in Real Time",
        "url": "https://www.404media.co/github-is-showing-the-trump-administration-scrubbing-government-web-pages-in-real-time/",
        "tags": ""
      }
    ]
  },
  {
    "section": "start-here",
    "links": [
      {
        "author": "George Orwell",
        "date": "1946",
        "title": "Politics and the English Language",
        "url": "https://www.orwellfoundation.com/the-orwell-foundation/orwell/essays-and-other-works/politics-and-the-english-language/"
      },
      {
        "author": "Dorothy Thompson, Harper's Magazine",
        "date": "1941",
        "title": "Who Goes Nazi?",
        "url": "https://harpers.org/archive/1941/08/who-goes-nazi/"
      },
      {
        "author": "U.S. Department of the Army",
        "date": "1947",
        "title": "Don't Be a Sucker",
        "url": "https://www.youtube.com/watch?v=vGAqYNFQdZ4"
      }
    ]
  },
  {
    "section": "further",
    "links": [
      {
        "author": "Wisecrack",
        "date": "07 Mar 2025",
        "title": "Democracy Is Collapsing: This 1971 Playbook Started It All",
        "url": "https://www.youtube.com/watch?v=HgYkde3o2Xw"
      },
      {
        "author": "Jason Stanley, Big Think",
        "date": "2021",
        "title": "The 10 Tactics of Fascism",
        "url": "https://www.youtube.com/watch?v=CpCKkWMbmXU"
      },
      {
        "author": "NYT Opinion",
        "date": "25 Jan 2025",
        "title": "The First Signs of Tyranny, From People Who Missed Them",
        "url": "https://www.youtube.com/watch?v=X_D-yW8v0Jo"
      },
      {
        "author": "Bernie Sanders",
        "date": "31 Jan 2025",
        "title": "We Are Living in Unprecedented Times",
        "url": "https://www.youtube.com/watch?v=mL0crkf5Dzw"
      },
      {
        "author": "Timothy Snyder (re-published by kottke.org)",
        "date": "2016",
        "title": "Fighting Authoritarianism: 20 Lessons from the 20th Century",
        "url": "https://kottke.org/16/11/fighting-authoritarianism-20-lessons-from-the-20th-century"
      },
      {
        "author": "Howard Zinn",
        "date": "1980, 2003",
        "title": "A People's History of the United States",
        "url": "https://files.libcom.org/files/A%20People's%20History%20of%20the%20Unite%20-%20Howard%20Zinn.pdf"
      }
    ]
  },
  {
    "section": "resources",
    "links": [
      {
        "text": "American Civil Liberties Union",
        "url": "https://www.aclu.org"
      },
      {
        "text": "Indivisible",
        "url": "https://indivisible.org"
      },
      {
        "text": "Southern Poverty Law Center",
        "url": "https://www.splcenter.org"
      }
    ]
  }
]
